fourier_mellin.cpython-312-x86_64-linux-gnu.so
fourier_mellin.libs/libopencv_aruco-60a67b09.so.4.5.2
fourier_mellin.libs/libopencv_bgsegm-5ad0bd95.so.4.5.2
fourier_mellin.libs/libopencv_bioinspired-541f1fd1.so.4.5.2
fourier_mellin.libs/libopencv_calib3d-29c5a288.so.4.5.2
fourier_mellin.libs/libopencv_ccalib-c2b70940.so.4.5.2
fourier_mellin.libs/libopencv_core-f9c7701c.so.4.5.2
fourier_mellin.libs/libopencv_datasets-eff16809.so.4.5.2
fourier_mellin.libs/libopencv_dnn-ceb98640.so.4.5.2
fourier_mellin.libs/libopencv_dnn_objdetect-aa51ba12.so.4.5.2
fourier_mellin.libs/libopencv_dnn_superres-6977c508.so.4.5.2
fourier_mellin.libs/libopencv_dpm-7deb769b.so.4.5.2
fourier_mellin.libs/libopencv_face-d59199a2.so.4.5.2
fourier_mellin.libs/libopencv_features2d-157f0ac9.so.4.5.2
fourier_mellin.libs/libopencv_flann-1b4008b2.so.4.5.2
fourier_mellin.libs/libopencv_fuzzy-a8500fe9.so.4.5.2
fourier_mellin.libs/libopencv_gapi-6cc039d8.so.4.5.2
fourier_mellin.libs/libopencv_hfs-7531aea3.so.4.5.2
fourier_mellin.libs/libopencv_highgui-6c2b0e4c.so.4.5.2
fourier_mellin.libs/libopencv_img_hash-eea4bb1c.so.4.5.2
fourier_mellin.libs/libopencv_imgcodecs-3ad27082.so.4.5.2
fourier_mellin.libs/libopencv_imgproc-282c35f4.so.4.5.2
fourier_mellin.libs/libopencv_intensity_transform-a955d13e.so.4.5.2
fourier_mellin.libs/libopencv_line_descriptor-e85934be.so.4.5.2
fourier_mellin.libs/libopencv_mcc-f6eaa021.so.4.5.2
fourier_mellin.libs/libopencv_ml-f40e084a.so.4.5.2
fourier_mellin.libs/libopencv_objdetect-bfc6cd5a.so.4.5.2
fourier_mellin.libs/libopencv_optflow-d5cddc2a.so.4.5.2
fourier_mellin.libs/libopencv_phase_unwrapping-1852fc77.so.4.5.2
fourier_mellin.libs/libopencv_photo-8f37febb.so.4.5.2
fourier_mellin.libs/libopencv_plot-923c38da.so.4.5.2
fourier_mellin.libs/libopencv_quality-be806f98.so.4.5.2
fourier_mellin.libs/libopencv_rapid-37e5571d.so.4.5.2
fourier_mellin.libs/libopencv_reg-bc9d5f98.so.4.5.2
fourier_mellin.libs/libopencv_rgbd-9bcb53c8.so.4.5.2
fourier_mellin-0.2.0.dist-info/METADATA
fourier_mellin-0.2.0.dist-info/WHEEL
fourier_mellin-0.2.0.dist-info/RECORD
fourier_mellin-0.2.0.dist-info/licenses/LICENSE
