Metadata-Version: 2.4
Name: fourier_mellin
Version: 0.2.0
Summary: Image Registration with Fourier Mellin using OpenCV
Author-email: htoik <henrik.toikka@aalto.fi>
Project-URL: Homepage, https://www.github.com/htoik/fourier-mellin
Classifier: Programming Language :: Python :: 3
Classifier: Programming Language :: C++
Classifier: License :: OSI Approved :: MIT License
Classifier: Operating System :: OS Independent
Requires-Python: >=3.7
License-File: LICENSE
Requires-Dist: numpy
Requires-Dist: opencv-python
Dynamic: license-file
